PyQuantum/py.py
PyQuantum/py2.py
PyQuantum/Bipartite/Cavity.py
PyQuantum/Bipartite/DensityMatrix.py
PyQuantum/Bipartite/Evolution.py
PyQuantum/Bipartite/FormHandler.py
PyQuantum/Bipartite/Hamiltonian.py
PyQuantum/Bipartite/Unitary.py
PyQuantum/Bipartite/WaveFunction.py
PyQuantum/Bipartite/__init__.py
PyQuantum/Bipartite/config.py
PyQuantum/Bipartite/config2.py
PyQuantum/Bipartite/config_backup.py
PyQuantum/Bipartite/make_config.py
PyQuantum/Bipartite/run.py
PyQuantum/BipartiteGeneral/Cavity.py
PyQuantum/BipartiteGeneral/DensityMatrix.py
PyQuantum/BipartiteGeneral/Evolution.py
PyQuantum/BipartiteGeneral/Hamiltonian.py
PyQuantum/BipartiteGeneral/Unitary.py
PyQuantum/BipartiteGeneral/WaveFunction.py
PyQuantum/BipartiteGeneral/__init__.py
PyQuantum/BipartiteGeneral/config.py
PyQuantum/BipartiteGeneralLindblad/Cavity.py
PyQuantum/BipartiteGeneralLindblad/DensityMatrix.py
PyQuantum/BipartiteGeneralLindblad/Evolution.py
PyQuantum/BipartiteGeneralLindblad/Hamiltonian.py
PyQuantum/BipartiteGeneralLindblad/Unitary.py
PyQuantum/BipartiteGeneralLindblad/WaveFunction.py
PyQuantum/BipartiteGeneralLindblad/__init__.py
PyQuantum/BipartiteGeneralLindblad/config.py
PyQuantum/BipartiteLindblad/Cavity.py
PyQuantum/BipartiteLindblad/DensityMatrix.py
PyQuantum/BipartiteLindblad/Evolution.py
PyQuantum/BipartiteLindblad/Hamiltonian.py
PyQuantum/BipartiteLindblad/Unitary.py
PyQuantum/BipartiteLindblad/WaveFunction.py
PyQuantum/BipartiteLindblad/__init__.py
PyQuantum/BipartiteLindblad/config.py
PyQuantum/Common/Assert.py
PyQuantum/Common/C_n_k.py
PyQuantum/Common/Fidelity.py
PyQuantum/Common/LoadPackage.py
PyQuantum/Common/Matrix.py
PyQuantum/Common/PlotBuilder3D.py
PyQuantum/Common/Print.py
PyQuantum/Common/PyPlot.py
PyQuantum/Common/PyPlot3d.py
PyQuantum/Common/PyPlot3dng.py
PyQuantum/Common/STR.py
PyQuantum/Common/Tools.py
PyQuantum/Common/__init__.py
PyQuantum/Common/ext.py
PyQuantum/Common/html.py
PyQuantum/TC/AtomicBase.py
PyQuantum/TC/Cavity.py
PyQuantum/TC/DensityMatrix.py
PyQuantum-1.0.60.dist-info/LICENSE
PyQuantum-1.0.60.dist-info/METADATA
PyQuantum-1.0.60.dist-info/WHEEL
PyQuantum-1.0.60.dist-info/entry_points.txt
PyQuantum-1.0.60.dist-info/top_level.txt
PyQuantum-1.0.60.dist-info/RECORD
