Metadata-Version: 2.1
Name: PyQuantum
Version: 1.0.60
Summary: Python3 module for Quantum Mechanics
Home-page: https://github.com/alexfmsu/PyQuantum
Author: alexfmsu
Author-email: alexfmsu@mail.ru
License: MIT
Platform: UNKNOWN
Classifier: License :: OSI Approved :: MIT License
Classifier: Programming Language :: Python :: 3
Classifier: Programming Language :: Python :: 3.7
Requires-Dist: importlib
Requires-Dist: matplotlib
Requires-Dist: numpy
Requires-Dist: pandas
Requires-Dist: plotly
Requires-Dist: scipy
